idem_csp/conf.py
idem_csp/version.py
idem_csp/acct/csp/token.py
idem_csp-2.0.0.dist-info/LICENSE
idem_csp-2.0.0.dist-info/METADATA
idem_csp-2.0.0.dist-info/WHEEL
idem_csp-2.0.0.dist-info/top_level.txt
idem_csp-2.0.0.dist-info/RECORD
