Metadata-Version: 2.1
Name: idem-csp
Version: 2.0.0
Summary: UNKNOWN
Home-page: UNKNOWN
Author: Tyler Johnson
Author-email: tyjohnson@vmware.com
License: UNKNOWN
Platform: UNKNOWN
Classifier: Environment :: Console
Classifier: Intended Audience :: Developers
Classifier: Intended Audience :: Information Technology
Classifier: Intended Audience :: System Administrators
Classifier: Operating System :: OS Independent
Classifier: Programming Language :: Python
Classifier: Programming Language :: Python :: 3.7
Classifier: Programming Language :: Python :: 3.8
Classifier: Programming Language :: Python :: 3.9
Classifier: Programming Language :: Python :: 3.10
Classifier: Development Status :: 5 - Production/Stable
Requires-Python: >=3.7
License-File: LICENSE
Requires-Dist: acct (>=6)
Requires-Dist: idem (>=11)
Requires-Dist: idem-aiohttp
Requires-Dist: pop (>=16.3)
